lazyslice/__init__.py
lazyslice/lazy_loading.py
lazyslice/version.py
lazyslice-0.3.0.dist-info/licenses/LICENSE
lazyslice-0.3.0.dist-info/METADATA
lazyslice-0.3.0.dist-info/WHEEL
lazyslice-0.3.0.dist-info/top_level.txt
lazyslice-0.3.0.dist-info/RECORD
