Metadata-Version: 2.4
Name: lazyslice
Version: 0.3.0
Summary: Lazy slicing and transpose operations for h5py and zarr
Author-email: Daniel Sotoude <dsot@protonmail.com>, Ben Dichter <ben.dichter@gmail.com>
Maintainer-email: Ben Dichter <ben.dichter@gmail.com>
License: BSD-3-Clause
Project-URL: Homepage, https://github.com/catalystneuro/lazyslice
Project-URL: Documentation, https://github.com/catalystneuro/lazyslice#readme
Project-URL: Repository, https://github.com/catalystneuro/lazyslice.git
Project-URL: Issues, https://github.com/catalystneuro/lazyslice/issues
Keywords: h5py,zarr,lazy,slicing,transpose,hdf5,numpy
Classifier: Development Status :: 4 - Beta
Classifier: Intended Audience :: Developers
Classifier: Intended Audience :: Science/Research
Classifier: License :: OSI Approved :: BSD License
Classifier: Operating System :: OS Independent
Classifier: Programming Language :: Python :: 3
Classifier: Programming Language :: Python :: 3.9
Classifier: Programming Language :: Python :: 3.10
Classifier: Programming Language :: Python :: 3.11
Classifier: Programming Language :: Python :: 3.12
Classifier: Topic :: Scientific/Engineering
Classifier: Typing :: Typed
Requires-Python: >=3.9
License-File: LICENSE
Requires-Dist: numpy>=1.20
Requires-Dist: h5py>=3.0
Provides-Extra: zarr
Requires-Dist: zarr>=2.10; extra == "zarr"
Provides-Extra: dev
Requires-Dist: pytest>=7.0; extra == "dev"
Requires-Dist: pytest-cov>=4.0; extra == "dev"
Requires-Dist: zarr>=2.10; extra == "dev"
Provides-Extra: docs
Requires-Dist: sphinx>=4.0; extra == "docs"
Requires-Dist: sphinx-rtd-theme>=1.0; extra == "docs"
Dynamic: license-file
